README.md
setup.cfg
setup.py
sco/__init__.py
sco/__main__.py
sco.egg-info/PKG-INFO
sco.egg-info/SOURCES.txt
sco.egg-info/dependency_links.txt
sco.egg-info/requires.txt
sco.egg-info/top_level.txt
sco/analysis/__init__.py
sco/analysis/core.py
sco/anatomy/__init__.py
sco/anatomy/core.py
sco/contrast/__init__.py
sco/contrast/core.py
sco/contrast/spyr.py
sco/impl/__init__.py
sco/impl/benson17/__init__.py
sco/impl/kay13/__init__.py
sco/impl/testing/__init__.py
sco/impl/testing/core.py
sco/model_comparison/__init__.py
sco/model_comparison/compare_with_Kay2013.py
sco/model_comparison/core.py
sco/model_comparison/py_to_matlab.py
sco/pRF/__init__.py
sco/pRF/core.py
sco/stimulus/__init__.py
sco/stimulus/core.py
sco/util/__init__.py
sco/util/io.py
sco/util/plot.py