Metadata-Version: 1.0
Name: sco
Version: 0.4.0
Summary: Library for the prediction of cortical responses to visual stimuli: the Standard Cortical Observer
Home-page: https://github.com/winawerlab/sco/
Author: Noah C. Benson
Author-email: nben@nyu.edu
License: GPLv3
Keywords: neuroscience vision cortex
Platform: UNKNOWN
